odoo/addons/account_invoice_download/README.rst
odoo/addons/account_invoice_download/__init__.py
odoo/addons/account_invoice_download/__manifest__.py
odoo/addons/account_invoice_download/data/cron.xml
odoo/addons/account_invoice_download/i18n/account_invoice_download.pot
odoo/addons/account_invoice_download/i18n/es.po
odoo/addons/account_invoice_download/i18n/nl.po
odoo/addons/account_invoice_download/models/__init__.py
odoo/addons/account_invoice_download/models/account_invoice_download_config.py
odoo/addons/account_invoice_download/models/account_invoice_download_log.py
odoo/addons/account_invoice_download/models/account_invoice_import_config.py
odoo/addons/account_invoice_download/readme/CONFIGURE.rst
odoo/addons/account_invoice_download/readme/CONTRIBUTORS.rst
odoo/addons/account_invoice_download/readme/DESCRIPTION.rst
odoo/addons/account_invoice_download/readme/INSTALL.rst
odoo/addons/account_invoice_download/security/ir.model.access.csv
odoo/addons/account_invoice_download/security/rule.xml
odoo/addons/account_invoice_download/static/description/icon.png
odoo/addons/account_invoice_download/static/description/index.html
odoo/addons/account_invoice_download/views/account_invoice_download_config.xml
odoo/addons/account_invoice_download/views/account_invoice_download_log.xml
odoo/addons/account_invoice_download/views/account_invoice_import_config.xml
odoo/addons/account_invoice_download/wizard/__init__.py
odoo/addons/account_invoice_download/wizard/account_invoice_download_credentials.py
odoo/addons/account_invoice_download/wizard/account_invoice_download_credentials_view.xml
odoo14_addon_account_invoice_download-14.0.1.1.0.dist-info/METADATA
odoo14_addon_account_invoice_download-14.0.1.1.0.dist-info/WHEEL
odoo14_addon_account_invoice_download-14.0.1.1.0.dist-info/top_level.txt
odoo14_addon_account_invoice_download-14.0.1.1.0.dist-info/RECORD
