Metadata-Version: 2.1
Name: odoo14-addon-account_invoice_download
Version: 14.0.1.1.0
Summary: Auto-download supplier invoices and import them
Home-page: https://github.com/OCA/edi
Author: Akretion,Odoo Community Association (OCA)
Author-email: support@odoo-community.org
License: AGPL-3
Classifier: Programming Language :: Python
Classifier: Framework :: Odoo
Classifier: Framework :: Odoo :: 14.0
Classifier: License :: OSI Approved :: GNU Affero General Public License v3
Requires-Python: >=3.6
Requires-Dist: odoo14-addon-account-invoice-import
Requires-Dist: odoo <14.1dev,>=14.0a
